README.md
setup.py
emailfinder/__init__.py
emailfinder/cli.py
emailfinder/core.py
emailfinder/extractor.py
emailfinder.egg-info/PKG-INFO
emailfinder.egg-info/SOURCES.txt
emailfinder.egg-info/dependency_links.txt
emailfinder.egg-info/entry_points.txt
emailfinder.egg-info/requires.txt
emailfinder.egg-info/top_level.txt
emailfinder/utils/__init__.py
emailfinder/utils/agent.py
emailfinder/utils/banner.py
emailfinder/utils/color_print.py
emailfinder/utils/exception.py
emailfinder/utils/library.py
emailfinder/utils/file/__init__.py
emailfinder/utils/file/email_parser.py
emailfinder/utils/finder/__init__.py
emailfinder/utils/finder/baidu.py
emailfinder/utils/finder/bing.py
emailfinder/utils/finder/google.py
emailfinder/utils/finder/yandex.py