Metadata-Version: 2.1
Name: emailfinder
Version: 0.2.2b0
Summary: EmailFinder - Emails search through Search Engines
Home-page: https://github.com/Josue87/EmailFinder
Author: Josue Encinar (@JosueEncinar)
License: GNU GPLv3+
Platform: UNKNOWN
